eztools/__init__.py
eztools/colors.py
eztools/files.py
eztools/logger.py
eztools/mathx.py
eztools/randomx.py
eztools/timer.py
eztools_kit-0.1.0.dist-info/METADATA
eztools_kit-0.1.0.dist-info/WHEEL
eztools_kit-0.1.0.dist-info/top_level.txt
eztools_kit-0.1.0.dist-info/RECORD
