Metadata-Version: 2.4
Name: eztools-kit
Version: 0.1.0
Summary: A lightweight utility toolkit for Python developers
Author: Wilder
Requires-Python: >=3.6
Dynamic: author
Dynamic: requires-python
Dynamic: summary
